cern-stubs/__init__.pyi
cern-stubs/accsoft/__init__.pyi
cern-stubs/accsoft/commons/__init__.pyi
cern-stubs/accsoft/commons/concurrent/__init__.pyi
cern-stubs/accsoft/commons/config/__init__.pyi
cern-stubs/accsoft/commons/config/coders/__init__.pyi
cern-stubs/accsoft/commons/diag/__init__.pyi
cern-stubs/accsoft/commons/diag/config/__init__.pyi
cern-stubs/accsoft/commons/diag/matcher/__init__.pyi
cern-stubs/accsoft/commons/diag/matcher/ccdb/__init__.pyi
cern-stubs/accsoft/commons/diag/matcher/cmw/__init__.pyi
cern-stubs/accsoft/commons/diag/matcher/cmw/fesa/__init__.pyi
cern-stubs/accsoft/commons/diag/matcher/japc/__init__.pyi
cern-stubs/accsoft/commons/diag/matcher/rbac/__init__.pyi
cern-stubs/accsoft/commons/diag/matcher/tgm/__init__.pyi
cern-stubs/accsoft/commons/domain/__init__.pyi
cern-stubs/accsoft/commons/domain/beamdestinations/__init__.pyi
cern-stubs/accsoft/commons/domain/beams/__init__.pyi
cern-stubs/accsoft/commons/domain/constants/__init__.pyi
cern-stubs/accsoft/commons/domain/constants/lhc/__init__.pyi
cern-stubs/accsoft/commons/domain/constants/ps/__init__.pyi
cern-stubs/accsoft/commons/domain/constants/psb/__init__.pyi
cern-stubs/accsoft/commons/domain/constants/sps/__init__.pyi
cern-stubs/accsoft/commons/domain/helper/__init__.pyi
cern-stubs/accsoft/commons/domain/lhc/__init__.pyi
cern-stubs/accsoft/commons/domain/modes/__init__.pyi
cern-stubs/accsoft/commons/domain/particletransfers/__init__.pyi
cern-stubs/accsoft/commons/domain/util/__init__.pyi
cern-stubs/accsoft/commons/domain/zones/__init__.pyi
cern-stubs/accsoft/commons/json/__init__.pyi
cern-stubs/accsoft/commons/remoting/__init__.pyi
cern-stubs/accsoft/commons/timing/__init__.pyi
cern-stubs/accsoft/commons/tracing/__init__.pyi
cern-stubs/accsoft/commons/tracing/aop/__init__.pyi
cern-stubs/accsoft/commons/tracing/aop/spi/__init__.pyi
cern-stubs/accsoft/commons/tracing/aop/spi/details/__init__.pyi
cern-stubs/accsoft/commons/tracing/aop/spi/stats/__init__.pyi
pjlsa-0.2.5.dist-info/METADATA
pjlsa-0.2.5.dist-info/WHEEL
pjlsa-0.2.5.dist-info/entry_points.txt
pjlsa-0.2.5.dist-info/top_level.txt
pjlsa-0.2.5.dist-info/RECORD
